instantly/template.py
instantly/instantly.py
instantly/settings.py
instantly/_first_template.py
instantly/__init__.py
instantly/main.py
instantly/service.py
instantpl-1.0.0.data/scripts/instantly
instantpl-1.0.0.dist-info/WHEEL
instantpl-1.0.0.dist-info/DESCRIPTION.rst
instantpl-1.0.0.dist-info/METADATA
instantpl-1.0.0.dist-info/pydist.json
instantpl-1.0.0.dist-info/top_level.txt
instantpl-1.0.0.dist-info/entry_points.txt
instantpl-1.0.0.dist-info/RECORD
