Metadata-Version: 2.0
Name: instantpl
Version: 1.0.0
Summary: A tool which allows you to create templates that can be expanded into full projects or stubs instantly.
Home-page: http://www.instantly.pl/
Author: Timothy Crosley
Author-email: timothy.crosley@gmail.com
License: MIT
Download-URL: https://github.com/timothycrosley/instantly/archive/1.0.0.tar.gz
Keywords: Accelerate,Python,Python2,Python3,Templating,Automate,Template,Snippet
Platform: UNKNOWN
Classifier: Development Status :: 4 - Beta
Classifier: Intended Audience :: Developers
Classifier: Natural Language :: English
Classifier: Environment :: Console
Classifier: License :: OSI Approved :: MIT License
Classifier: Programming Language :: Python
Classifier: Programming Language :: Python :: 2
Classifier: Programming Language :: Python :: 2.6
Classifier: Programming Language :: Python :: 2.7
Classifier: Programming Language :: Python :: 3
Classifier: Programming Language :: Python :: 3.0
Classifier: Programming Language :: Python :: 3.1
Classifier: Programming Language :: Python :: 3.2
Classifier: Programming Language :: Python :: 3.3
Classifier: Topic :: Software Development :: Libraries
Classifier: Topic :: Utilities
Requires: configobj
Requires: requests
Requires: pies
Requires-Dist: configobj
Requires-Dist: requests
Requires-Dist: pies (>=2.6.1)
